{
  "id": "sass-eventos-api-environment",
  "name": "SASS Eventos API - Development",
  "values": [
    {
      "key": "baseUrl",
      "value": "http://localhost:3000",
      "type": "default",
      "enabled": true,
      "description": "URL base del servidor de desarrollo"
    },
    {
      "key": "geographyId",
      "value": "1",
      "type": "default", 
      "enabled": true,
      "description": "ID de geografía de ejemplo para las pruebas"
    },
    {
      "key": "buId",
      "value": "1",
      "type": "default",
      "enabled": true,
      "description": "ID de Business Unit de ejemplo para las pruebas"
    },
    {
      "key": "cfsId",
      "value": "1",
      "type": "default",
      "enabled": true,
      "description": "ID de CFS de ejemplo para las pruebas"
    },
    {
      "key": "disciplinaId",
      "value": "1",
      "type": "default",
      "enabled": true,
      "description": "ID de disciplina de ejemplo para las pruebas"
    },
    {
      "key": "statusModeloId",
      "value": "1",
      "type": "default",
      "enabled": true,
      "description": "ID de status modelo de ejemplo para las pruebas"
    },
    {
      "key": "modeloContribuyenteId",
      "value": "1",
      "type": "default",
      "enabled": true,
      "description": "ID de modelo contribuyente de ejemplo para las pruebas"
    },
    {
      "key": "operativaId",
      "value": "1",
      "type": "default",
      "enabled": true,
      "description": "ID de operativa de ejemplo para las pruebas"
    },
    {
      "key": "metricaImpactoId",
      "value": "1",
      "type": "default",
      "enabled": true,
      "description": "ID de métrica de impacto de ejemplo para las pruebas"
    },
    {
      "key": "incidenciaId",
      "value": "1",
      "type": "default",
      "enabled": true,
      "description": "ID de incidencia de ejemplo para las pruebas"
    },
    {
      "key": "serviceOwnerId",
      "value": "1",
      "type": "default",
      "enabled": true,
      "description": "ID de service owner de ejemplo para las pruebas"
    },
    {
      "key": "statusMedicionId",
      "value": "1",
      "type": "default",
      "enabled": true,
      "description": "ID de status medición de ejemplo para las pruebas"
    },
    {
      "key": "partnershipId",
      "value": "1",
      "type": "default",
      "enabled": true,
      "description": "ID de partnership de ejemplo para las pruebas"
    },
    {
      "key": "modeloEventoId",
      "value": "1",
      "type": "default",
      "enabled": true,
      "description": "ID de modelo evento de ejemplo para las pruebas"
    },
    {
      "key": "CONFIRM_FULL_ROLLBACK",
      "value": "",
      "type": "default",
      "enabled": false,
      "description": "⚠️ SEGURIDAD: Establece a 'YES_DELETE_ALL_DATA' para permitir rollback completo. SOLO EN DESARROLLO."
    }
  ],
  "_postman_variable_scope": "environment"
}
